LICENSE.txt
MANIFEST.in
README.md
setup.cfg
setup.py
svox/__init__.py
svox/helpers.py
svox/renderer.py
svox/sg.py
svox/sh.py
svox/svox.py
svox/version.py
svox.egg-info/PKG-INFO
svox.egg-info/SOURCES.txt
svox.egg-info/dependency_links.txt
svox.egg-info/not-zip-safe
svox.egg-info/top_level.txt
svox/csrc/quantizer.cpp
svox/csrc/rt_kernel.cu
svox/csrc/svox.cpp
svox/csrc/svox_kernel.cu
svox/csrc/include/common.cuh
svox/csrc/include/data_spec.hpp
svox/csrc/include/data_spec_packed.cuh
test/test_64.py
test/test_backward.py
test/test_basic.py
test/test_ccorner.py
test/test_child.py
test/test_double.py
test/test_expand.py
test/test_hessian.py
test/test_llff.py
test/test_llff2.py
test/test_mse.py
test/test_quant.py
test/test_quant_on_im.py
test/test_render.py
test/test_render_backward.py
test/test_render_sanity.py
test/test_render_with_ray.py
test/test_simple.py
test/test_weight_accum.py