Metadata-Version: 1.0
Name: svox
Version: 0.2.32
Summary: Sparse voxel N^3-tree data structure using CUDA
Home-page: UNKNOWN
Author: Alex Yu
Author-email: alexyu99126@gmail.com
License: UNKNOWN
Platform: UNKNOWN
